README.txt
setup.cfg
setup.py
docs/HISTORY.txt
docs/LICENSE.GPL
docs/LICENSE.txt
valentine/__init__.py
valentine.imagescales.egg-info/PKG-INFO
valentine.imagescales.egg-info/SOURCES.txt
valentine.imagescales.egg-info/dependency_links.txt
valentine.imagescales.egg-info/entry_points.txt
valentine.imagescales.egg-info/namespace_packages.txt
valentine.imagescales.egg-info/not-zip-safe
valentine.imagescales.egg-info/requires.txt
valentine.imagescales.egg-info/top_level.txt
valentine/imagescales/README.txt
valentine/imagescales/__init__.py
valentine/imagescales/configure.zcml
valentine/imagescales/patches.py
valentine/imagescales/profiles.zcml
valentine/imagescales/traverse.py
valentine/imagescales/version.txt
valentine/imagescales/Extensions/Install.py
valentine/imagescales/browser/__init__.py
valentine/imagescales/browser/atfield.py
valentine/imagescales/browser/atfield.txt
valentine/imagescales/browser/atfield.zcml
valentine/imagescales/browser/atfolder.py
valentine/imagescales/browser/atfolder.txt
valentine/imagescales/browser/atfolder.zcml
valentine/imagescales/browser/attopic.txt
valentine/imagescales/browser/attopic.zcml
valentine/imagescales/browser/configure.zcml
valentine/imagescales/browser/interfaces.py
valentine/imagescales/browser/multimedia.py
valentine/imagescales/browser/multimedia.txt
valentine/imagescales/browser/multimedia.zcml
valentine/imagescales/browser/images/play-button.png
valentine/imagescales/tests/__init__.py
valentine/imagescales/tests/base.py
valentine/imagescales/tests/testScaleTraverser.py
valentine/imagescales/tests/data/barsandtone.flv
valentine/imagescales/tests/data/test.png
valentine/imagescales/tests/data/test.tif