Metadata-Version: 1.0
Name: valentine.imagescales
Version: 0.2.1
Summary: UNKNOWN
Home-page: https://svn.plone.org/svn/collective/valentine.imagescales/trunk
Author: Per Thulin
Author-email: per.thulin at valentinewebsystems dot se
License: GPL
Platform: UNKNOWN
Classifier: Programming Language :: Python
Classifier: Topic :: Software Development :: Libraries :: Python Modules
